commonmodel/__init__.py
commonmodel/base.py
commonmodel/field_types.py
commonmodel/utils.py
common_model-0.5.2.dist-info/LICENSE
common_model-0.5.2.dist-info/WHEEL
common_model-0.5.2.dist-info/METADATA
common_model-0.5.2.dist-info/RECORD
