Metadata-Version: 2.1
Name: common-model
Version: 0.5.2
Summary: Universal Data Schemas
License: BSD-3-Clause
Author: Ken Van Haren
Author-email: kenvanharen@gmail.com
Requires-Python: >=3.7
Classifier: License :: OSI Approved :: BSD License
Classifier: Programming Language :: Python :: 3
Classifier: Programming Language :: Python :: 3.7
Classifier: Programming Language :: Python :: 3.8
Classifier: Programming Language :: Python :: 3.9
Classifier: Programming Language :: Python :: 3.10
Classifier: Programming Language :: Python :: 3.11
Requires-Dist: PyYAML (>=5.4.1)
Requires-Dist: pydantic (>=1.8.1)
